Metadata-Version: 2.1
Name: ddinsta
Version: 0.1
Summary: Module for downloading photos and videos from Instagram
Home-page: https://github.com/zingiev/ddinsta
Author: Yasin Zingiev (Rocket)
Author-email: m@zingiev.ru
License: MIT
License-File: LICENSE
Requires-Dist: requests
